schemist/__init__.py
schemist/cleaning.py
schemist/cli.py
schemist/collating.py
schemist/converting.py
schemist/features.py
schemist/generating.py
schemist/http.py
schemist/io.py
schemist/rest_lookup.py
schemist/sanifix5.py
schemist/splitting.py
schemist/tables.py
schemist/typing.py
schemist-0.0.6.dist-info/licenses/LICENSE
schemist-0.0.6.dist-info/METADATA
schemist-0.0.6.dist-info/WHEEL
schemist-0.0.6.dist-info/entry_points.txt
schemist-0.0.6.dist-info/top_level.txt
schemist-0.0.6.dist-info/RECORD
