Metadata-Version: 2.4
Name: schemist
Version: 0.0.6
Summary: Organizing and processing tables of chemical structures.
Author-email: Eachan Johnson <eachan.johnson@crick.ac.uk>
License: MIT License
Project-URL: Homepage, https://github.com/scbirlab/schemist
Project-URL: Repository, https://github.com/scbirlab/schemist.git
Project-URL: Bug Tracker, https://github.com/scbirlab/schemist/issues
Project-URL: Documentation, https://readthedocs.org/schemist
Keywords: science,chemistry,SMILES,SELFIES,cheminformatics
Classifier: Development Status :: 3 - Alpha
Classifier: Intended Audience :: Science/Research
Classifier: Topic :: Scientific/Engineering :: Chemistry
Classifier: License :: OSI Approved :: MIT License
Classifier: Programming Language :: Python :: 3.9
Classifier: Programming Language :: Python :: 3.10
Classifier: Programming Language :: Python :: 3.11
Classifier: Programming Language :: Python :: 3.12
Classifier: Programming Language :: Python :: 3.13
Classifier: Programming Language :: Python :: 3 :: Only
Requires-Python: >=3.8
License-File: LICENSE
Requires-Dist: carabiner-tools[pd]>=0.0.4
Requires-Dist: descriptastorus>=2.7
Requires-Dist: nemony
Requires-Dist: openpyxl==3.1.0
Requires-Dist: pandas
Requires-Dist: rdkit>=2022.09.5
Requires-Dist: requests
Requires-Dist: selfies
Provides-Extra: old-glibc
Requires-Dist: rdkit-pypi==2022.09.5; extra == "old-glibc"
Provides-Extra: dev
Requires-Dist: pytest; extra == "dev"
Requires-Dist: flake8; extra == "dev"
Dynamic: license-file
